ebook_toc-0.0.1a0.dist-info/METADATA
ebook_toc-0.0.1a0.dist-info/WHEEL
ebook_toc-0.0.1a0.dist-info/entry_points.txt
ebooktoc/__init__.py
ebooktoc/cli.py
ebooktoc/fingerprints.py
ebooktoc/pdf_writer.py
ebooktoc/siliconflow_api.py
ebooktoc/toc_parser.py
ebooktoc/utils.py
ebook_toc-0.0.1a0.dist-info/RECORD
