Metadata-Version: 2.1
Name: ebook-toc
Version: 0.0.1a0
Summary: CLI tool to extract PDF table of contents using SiliconFlow Qwen/Qwen3-VL-32B-Instruct
Author: Pi
Requires-Python: >=3.10
Requires-Dist: requests>=2.31.0
Requires-Dist: rich>=13.0.0
Requires-Dist: pymupdf>=1.23.0; python_version < "3.14"
